light_side/.config.yaml
light_side/__about__.py
light_side/__init__.py
light_side/core.py
light_side/module.py
light_side/utils.py
light_side/version.py
light_side/api/__init__.py
light_side/archs/__init__.py
light_side/archs/zerodce/__init__.py
light_side/archs/zerodce/module.py
light_side/archs/zerodce/blocks/__init__.py
light_side/archs/zerodce/blocks/dce.py
light_side/archs/zerodce/blocks/loss.py
light_side/datasets/__init__.py
light_side/datasets/base.py
light_side/datasets/zerodce.py
light_side/models/.gitkeep
light_side/models/zerodce_3-32-16_zerodce/.gitkeep
light_side/models/zerodce_3-32-16_zerodce/v0/.gitkeep
light_side/models/zerodce_3-32-16_zerodce/v1/.gitkeep
light_side/models/zerodce_7-16-8_zerodce/.gitkeep
light_side/models/zerodce_7-16-8_zerodce/v0/.gitkeep
light_side/models/zerodce_7-16-8_zerodce/v1/.gitkeep
light_side/models/zerodce_7-32-16_zerodce/.gitkeep
light_side/models/zerodce_7-32-16_zerodce/v0/.gitkeep
light_side/models/zerodce_7-32-16_zerodce/v1/.gitkeep
light_side/models/zerodce_7-32-8_zerodce/.gitkeep
light_side/models/zerodce_7-32-8_zerodce/v0/.gitkeep
light_side/models/zerodce_7-32-8_zerodce/v1/.gitkeep
scripts/__init__.py
scripts/release.py
light_side-0.1.0.dist-info/LICENSE
light_side-0.1.0.dist-info/METADATA
light_side-0.1.0.dist-info/WHEEL
light_side-0.1.0.dist-info/top_level.txt
light_side-0.1.0.dist-info/RECORD
